jupyterlab_firefox_launcher/__init__.py
jupyterlab_firefox_launcher/_version.py
jupyterlab_firefox_launcher/firefox_handler.py
jupyterlab_firefox_launcher/server_extension.py
jupyterlab_firefox_launcher/server_proxy.py
jupyterlab_firefox_launcher/templates/dependency_error.html
jupyterlab_firefox_launcher-0.9.10.data/data/bin/firefox-xstartup
jupyterlab_firefox_launcher-0.9.10.data/data/etc/jupyter/jupyter_server_config.d/jupyterlab_firefox_launcher.json
jupyterlab_firefox_launcher-0.9.10.data/data/share/jupyter/labextensions/jupyterlab-firefox-launcher/install.json
jupyterlab_firefox_launcher-0.9.10.data/data/share/jupyter/labextensions/jupyterlab-firefox-launcher/package.json
jupyterlab_firefox_launcher-0.9.10.data/data/share/jupyter/labextensions/jupyterlab-firefox-launcher/static/3c09952b57aec9ff2c33.svg
jupyterlab_firefox_launcher-0.9.10.data/data/share/jupyter/labextensions/jupyterlab-firefox-launcher/static/407.04b6a602683ddf1a2095.js
jupyterlab_firefox_launcher-0.9.10.data/data/share/jupyter/labextensions/jupyterlab-firefox-launcher/static/remoteEntry.1f093b876581ea691c9b.js
jupyterlab_firefox_launcher-0.9.10.data/data/share/jupyter/labextensions/jupyterlab-firefox-launcher/static/style.js
jupyterlab_firefox_launcher-0.9.10.data/data/share/jupyter/labextensions/jupyterlab-firefox-launcher/static/third-party-licenses.json
jupyterlab_firefox_launcher-0.9.10.dist-info/METADATA
jupyterlab_firefox_launcher-0.9.10.dist-info/WHEEL
jupyterlab_firefox_launcher-0.9.10.dist-info/entry_points.txt
jupyterlab_firefox_launcher-0.9.10.dist-info/licenses/LICENSE
jupyterlab_firefox_launcher-0.9.10.dist-info/RECORD
