Metadata-Version: 2.4
Name: jupyterlab-firefox-launcher
Version: 0.9.10
Summary: JupyterLab extension to launch Firefox in a tab
Project-URL: Homepage, https://github.com/vantagecompute/jupyterlab-firefox-launcher
Project-URL: Documentation, https://github.com/vantagecompute/jupyterlab-firefox-launcher
Project-URL: Repository, https://github.com/vantagecompute/jupyterlab-firefox-launcher.git
Project-URL: Changelog, https://github.com/vantagecompute/jupyterlab-firefox-launcher/blob/main/CHANGELOG.md
Author-email: James Beedy <james@vantagecompute.ai>
License:                                  Apache License
License-File: LICENSE
Keywords: Browser,Extension,Firefox,Jupyter,JupyterLab,JupyterLab4
Classifier: Framework :: Jupyter
Classifier: Framework :: Jupyter :: JupyterLab
Classifier: Framework :: Jupyter :: JupyterLab :: 4
Classifier: Framework :: Jupyter :: JupyterLab :: Extensions
Classifier: License :: OSI Approved :: BSD License
Classifier: Programming Language :: Python
Classifier: Programming Language :: Python :: 3.10
Classifier: Programming Language :: Python :: 3.11
Classifier: Programming Language :: Python :: 3.12
Requires-Python: >=3.10
Requires-Dist: jupyter-server-proxy>=3.0.0
Requires-Dist: jupyter-server<3,>=2.0.1
Requires-Dist: jupyterlab>=4.4.5
Requires-Dist: psutil
Requires-Dist: python-uinput>=1.0.1
Requires-Dist: tornado>=6.1.0
Provides-Extra: dev
Requires-Dist: build; extra == 'dev'
Requires-Dist: codespell; extra == 'dev'
Requires-Dist: coverage; extra == 'dev'
Requires-Dist: hatch; extra == 'dev'
Requires-Dist: jupyter-packaging<1,>=0.12; extra == 'dev'
Requires-Dist: jupyterlab<5,>=4.0.0; extra == 'dev'
Requires-Dist: pyright; extra == 'dev'
Requires-Dist: pytest; extra == 'dev'
Requires-Dist: pytest-asyncio; extra == 'dev'
Requires-Dist: pytest-cov; extra == 'dev'
Requires-Dist: pytest-jupyter[server]>=0.4; extra == 'dev'
Requires-Dist: ruff; extra == 'dev'
